ichingshifa/__init__.py
ichingshifa/data.pkl
ichingshifa/ichingshifa.py
ichingshifa-3.1.9.dist-info/METADATA
ichingshifa-3.1.9.dist-info/WHEEL
ichingshifa-3.1.9.dist-info/top_level.txt
ichingshifa-3.1.9.dist-info/RECORD
