Metadata-Version: 2.1
Name: ichingshifa
Version: 3.1.9
Summary: A package of iching stalk divination in Traditional Chinese Language. Python周易筮法，納甲六爻，起卦不求人。
Home-page: https://github.com/kentang2017/iching_shifa
Author: Ken Tang
Author-email: kinyeah@gmail.com
Classifier: Programming Language :: Python :: 3
Classifier: License :: OSI Approved :: MIT License
Classifier: Operating System :: OS Independent
